flat_ai/__about__.py
flat_ai/__init__.py
flat_ai/flat_ai.py
flat_ai/function_helpers.py
flat_ai/trace_llm.py
flat_ai-0.4.0.dist-info/LICENSE
flat_ai-0.4.0.dist-info/METADATA
flat_ai-0.4.0.dist-info/WHEEL
flat_ai-0.4.0.dist-info/top_level.txt
flat_ai-0.4.0.dist-info/RECORD
